getiprompt/__init__.py
getiprompt-0.1.0.dist-info/METADATA
getiprompt-0.1.0.dist-info/WHEEL
getiprompt-0.1.0.dist-info/licenses/LICENSE
getiprompt-0.1.0.dist-info/RECORD
